ALU.v
module ALU (
    input  [7:0] A,
    input  [7:0] B,
    input  [2:0] opcode,
    output reg [7:0] Result,
    output reg Carry,
    output reg Zero
);

always @(*) begin
    Carry = 0;
    case (opcode)
        3'b000: {Carry, Result} = A + B;      // ADD
        3'b001: {Carry, Result} = A - B;      // SUB
        3'b010: Result = A & B;               // AND
        3'b011: Result = A | B;               // OR
        3'b100: Result = A ^ B;               // XOR
        3'b101: Result = ~(A | B);            // NOR
        3'b110: Result = A << 1;              // SHIFT LEFT
        3'b111: Result = A >> 1;              // SHIFT RIGHT
        default: Result = 8'b00000000;
    endcase

    Zero = (Result == 0);
end

endmodule

alu_wave.vcd
$version Generated by VerilatedVcd $end
$timescale 1ps $end
 $scope module TOP $end
  $var wire 8 # A [7:0] $end
  $var wire 8 $ B [7:0] $end
  $var wire 3 % opcode [2:0] $end
  $var wire 8 & Result [7:0] $end
  $var wire 1 ' Carry $end
  $var wire 1 ( Zero $end
  $scope module ALU $end
   $var wire 8 # A [7:0] $end
   $var wire 8 $ B [7:0] $end
   $var wire 3 % opcode [2:0] $end
   $var wire 8 & Result [7:0] $end
   $var wire 1 ' Carry $end
   $var wire 1 ( Zero $end
  $upscope $end
 $upscope $end
$enddefinitions $end


#0
b10101000 #
b10010010 $
b000 %
b00111010 &
1'
0(
#10
b001 %
b00010110 &
0'
#20
b010 %
b10000000 &
#30
b011 %
b10111010 &
#40
b100 %
b00111010 &
#50
b101 %
b01000101 &
#60
b110 %
b01010000 &
#70
b111 %
b01010100 &
#80
b01110001 #
b01110100 $
b000 %
b11100101 &
#90
b001 %
b11111101 &
1'
#100
b010 %
b01110000 &
0'
#110
b011 %
b01110101 &
#120
b100 %
b00000101 &
#130
b101 %
b10001010 &
#140
b110 %
b11100010 &
#150
b111 %
b00111000 &
#160
b10111110 #
b11110010 $
b000 %
b10110000 &
1'
#170
b001 %
b11001100 &
#180
b010 %
b10110010 &
0'
#190
b011 %
b11111110 &
#200
b100 %
b01001100 &
#210
b101 %
b00000001 &
#220
b110 %
b01111100 &
#230
b111 %
b01011111 &
#240
b01110111 #
b10101010 $
b000 %
b00100001 &
1'
#250
b001 %
b11001101 &
#260
b010 %
b00100010 &
0'
#270
b011 %
b11111111 &
#280
b100 %
b11011101 &
#290
b101 %
b00000000 &
1(
#300
b110 %
b11101110 &
0(
#310
b111 %
b00111011 &
#320
b00111010 #
b11001001 $
b000 %
b00000011 &
1'
#330
b001 %
b01110001 &
#340
b010 %
b00001000 &
0'
#350
b011 %
b11111011 &
#360
b100 %
b11110011 &
#370
b101 %
b00000100 &
#380
b110 %
b01110100 &
#390
b111 %
b00011101 &
#400
b11111001 #
b00010100 $
b000 %
b00001101 &
1'
#410
b001 %
b11100101 &
0'
#420
b010 %
b00010000 &
#430
b011 %
b11111101 &
#440
b100 %
b11101101 &
#450
b101 %
b00000010 &
#460
b110 %
b11110010 &
#470
b111 %
b01111100 &
#480
b10100000 #
b10110111 $
b000 %
b01010111 &
1'
#490
b001 %
b11101001 &
#500
b010 %
b10100000 &
0'
#510
b011 %
b10110111 &
#520
b100 %
b00010111 &
#530
b101 %
b01001000 &
#540
b110 %
b01000000 &
#550
b111 %
b01010000 &
#560
b00011110 #
b10101101 $
b000 %
b11001011 &
#570
b001 %
b01110001 &
1'
#580
b010 %
b00001100 &
0'
#590
b011 %
b10111111 &
#600
b100 %
b10110011 &
#610
b101 %
b01000000 &
#620
b110 %
b00111100 &
#630
b111 %
b00001111 &
#640
b10100010 #
b11000011 $
b000 %
b01100101 &
1'
#650
b001 %
b11011111 &
#660
b010 %
b10000010 &
0'
#670
b011 %
b11100011 &
#680
b100 %
b01100001 &
#690
b101 %
b00011100 &
#700
b110 %
b01000100 &
#710
b111 %
b01010001 &
#720
b00011000 #
b11100011 $
b000 %
b11111011 &
#730
b001 %
b00110101 &
1'
#740
b010 %
b00000000 &
0'
1(
#750
b011 %
b11111011 &
0(
#760
b100 %
#770
b101 %
b00000100 &
#780
b110 %
b00110000 &
#790
b111 %
b00001100 &
